<?xml version="1.0" encoding="UTF-8"?>
<!DOCTYPE hibernate-mapping PUBLIC "-//Hibernate/Hibernate Mapping DTD 3.0//EN" "http://www.hibernate.org/dtd/hibernate-mapping-3.0.dtd">
<!-- Generated 13/01/2016 07:08:11 PM by Hibernate Tools 3.2.2.GA -->
<hibernate-mapping>
  <class name="pe.edu.upn.encuesta.entidad.RolOpcion" table="ROL_COMPONENTE">
    <id name="id" type="long">
      <column name="ID" precision="10" scale="0"/>
      <generator class="sequence">
        <param name="sequence">SQ_ROL_COMPONENTE</param>
      </generator>
    </id>
    <property name="rolIdm" type="string">
      <column length="25" name="ROL_IDM" not-null="true"/>
    </property>
    <property name="invisible" type="string">
      <column length="1" name="INVISIBLE" not-null="true"/>
    </property>
    <property name="inactivo" type="string">
      <column length="1" name="INACTIVO" not-null="true"/>
    </property>
    <many-to-one class="pe.edu.upn.encuesta.entidad.Modulo" fetch="join" name="modulo">
      <column name="COMPONENTE_ID" precision="10" scale="0"/>
    </many-to-one>
    <property name="estado" type="string">
      <column length="1" name="ESTADO" not-null="true"/>
    </property>
    <property name="usuarioCreacion" type="string">
      <column length="7" name="USUARIO_CREACION" not-null="true"/>
    </property>
    <property name="fechaCreacion" type="timestamp">
      <column length="11" name="FECHA_CREACION" not-null="true"/>
    </property>
    <property name="usuarioModificacion" type="string">
      <column length="7" name="USUARIO_MODIFICACION"/>
    </property>
    <property name="fechaModificacion" type="timestamp">
      <column length="11" name="FECHA_MODIFICACION"/>
    </property>
  </class>
  <query name="obtenerOpcionesPorRoles">
    	select distinct t,m
		from RolOpcion t join t.modulo m
		where t.rolIdm IN (:listaRoles) and t.estado='A'
		ORDER BY m.id asc
    </query>
</hibernate-mapping>
